kcounter-0.1.1.dist-info/METADATA
kcounter-0.1.1.dist-info/WHEEL
kcounter.cpython-311-darwin.so
kcounter-0.1.1.dist-info/RECORD
