Metadata-Version: 2.1
Name: kcounter
Version: 0.1.1
Keywords: kmer bioinformatics
Home-Page: https://github.com/apcamargo/kcounter
Author: Antonio Camargo <antoniop.camargo@gmail.com>
Author-Email: Antonio Camargo <antoniop.camargo@gmail.com>
